<annotation>
	<folder>one</folder>
	<filename>one.0f1b5fc0-6124-11ee-81dc-8502e4cc58f0.jpg</filename>
	<path>C:\Users\user\Tensorflow\workspace\images\Train\one\one.0f1b5fc0-6124-11ee-81dc-8502e4cc58f0.jpg</path>
	<source>
		<database>Unknown</database>
	</source>
	<size>
		<width>640</width>
		<height>480</height>
		<depth>3</depth>
	</size>
	<segmented>0</segmented>
	<object>
		<name>one</name>
		<pose>Unspecified</pose>
		<truncated>0</truncated>
		<difficult>0</difficult>
		<bndbox>
			<xmin>131</xmin>
			<ymin>126</ymin>
			<xmax>281</xmax>
			<ymax>400</ymax>
		</bndbox>
	</object>
</annotation>
